nlp_provider/__init__.py
nlp_provider-0.1.0.dist-info/WHEEL
nlp_provider-0.1.0.dist-info/METADATA
nlp_provider-0.1.0.dist-info/RECORD
